{
  "company_id": "recruit",
  "name": "Recruit Holdings Co., Ltd.",
  "ticker": "6098",
  "exchange": "TSE",
  "currency": "JPY",
  "reporting_unit": "billions",
  "fiscal_year_end_month": 3,
  "ir_url": "https://recruit-holdings.com/ir/",
  "last_updated": "2025-04-14T00:00:00Z",
  "periods": [
    {
      "period_type": "FY",
      "fiscal_year": 2020,
      "fiscal_quarter": null,
      "period_label": "FY2020",
      "start_date": "2019-04-01",
      "end_date": "2020-03-31",
      "calendar_year": 2020,
      "currency": "JPY",
      "usd_rate": 0.009330,
      "revenue": 2099,
      "gross_profit": 1390,
      "operating_income": 163,
      "ebitda": 281,
      "net_income": 153,
      "total_assets": 2180,
      "total_equity": 1120,
      "total_debt": 218,
      "cash_and_equivalents": 540,
      "operating_cash_flow": 280,
      "capex": 58,
      "free_cash_flow": 222,
      "paid_users": null,
      "arpu": null
    },
    {
      "period_type": "FY",
      "fiscal_year": 2021,
      "fiscal_quarter": null,
      "period_label": "FY2021",
      "start_date": "2020-04-01",
      "end_date": "2021-03-31",
      "calendar_year": 2021,
      "currency": "JPY",
      "usd_rate": 0.009510,
      "revenue": 1989,
      "gross_profit": 1310,
      "operating_income": 112,
      "ebitda": 242,
      "net_income": 156,
      "total_assets": 2340,
      "total_equity": 1260,
      "total_debt": 198,
      "cash_and_equivalents": 620,
      "operating_cash_flow": 255,
      "capex": 52,
      "free_cash_flow": 203,
      "paid_users": null,
      "arpu": null
    },
    {
      "period_type": "FY",
      "fiscal_year": 2022,
      "fiscal_quarter": null,
      "period_label": "FY2022",
      "start_date": "2021-04-01",
      "end_date": "2022-03-31",
      "calendar_year": 2022,
      "currency": "JPY",
      "usd_rate": 0.008710,
      "revenue": 2841,
      "gross_profit": 1920,
      "operating_income": 380,
      "ebitda": 520,
      "net_income": 281,
      "total_assets": 2920,
      "total_equity": 1590,
      "total_debt": 188,
      "cash_and_equivalents": 740,
      "operating_cash_flow": 450,
      "capex": 65,
      "free_cash_flow": 385,
      "paid_users": null,
      "arpu": null
    },
    {
      "period_type": "FY",
      "fiscal_year": 2023,
      "fiscal_quarter": null,
      "period_label": "FY2023",
      "start_date": "2022-04-01",
      "end_date": "2023-03-31",
      "calendar_year": 2023,
      "currency": "JPY",
      "usd_rate": 0.007360,
      "revenue": 3238,
      "gross_profit": 2200,
      "operating_income": 436,
      "ebitda": 596,
      "net_income": 320,
      "total_assets": 3380,
      "total_equity": 1840,
      "total_debt": 178,
      "cash_and_equivalents": 870,
      "operating_cash_flow": 520,
      "capex": 72,
      "free_cash_flow": 448,
      "paid_users": null,
      "arpu": null
    },
    {
      "period_type": "FY",
      "fiscal_year": 2024,
      "fiscal_quarter": null,
      "period_label": "FY2024",
      "start_date": "2023-04-01",
      "end_date": "2024-03-31",
      "calendar_year": 2024,
      "currency": "JPY",
      "usd_rate": 0.006712,
      "revenue": 3484,
      "gross_profit": 2380,
      "operating_income": 472,
      "ebitda": 645,
      "net_income": 345,
      "total_assets": 3620,
      "total_equity": 2080,
      "total_debt": 160,
      "cash_and_equivalents": 980,
      "operating_cash_flow": 580,
      "capex": 78,
      "free_cash_flow": 502,
      "paid_users": null,
      "arpu": null
    }
  ]
}
